oglhclient
