Metadata-Version: 1.1
Name: oglhclient
Version: 1.0.0
Summary: An API client library for Opengear Lighthouse
Home-page: https://github.com/opengear/oglhclient
Author: Lighthouse Team
Author-email: engineering@opengear.com
License: UNKNOWN
Download-URL: https://github.com/opengear/oglhclient/archive/v1.0.0.tar.gz
Keywords: api,opengear,lighthouse
Platform: UNKNOWN
Classifier: Programming Language :: Python :: 3
Classifier: Programming Language :: Python :: 2
